fh_posts/__init__.py
fh_posts/_modidx.py
fh_posts/all.py
fh_posts/core.py
fh_posts-0.0.3.dist-info/LICENSE
fh_posts-0.0.3.dist-info/METADATA
fh_posts-0.0.3.dist-info/WHEEL
fh_posts-0.0.3.dist-info/entry_points.txt
fh_posts-0.0.3.dist-info/top_level.txt
fh_posts-0.0.3.dist-info/RECORD
