Metadata-Version: 2.2
Name: fh_posts
Version: 0.0.3
Summary: Turn Markdown and Jupyter Notebooks into dynamic FastHTML posts with smart YAML parsing and live Python execution.
Home-page: https://github.com/decherd/fh_posts
Author: Drew Echerd
Author-email: drewecherd@gmail.com
License: Apache Software License 2.0
Keywords: nbdev jupyter notebook python
Classifier: Development Status :: 4 - Beta
Classifier: Intended Audience :: Developers
Classifier: Natural Language :: English
Classifier: Programming Language :: Python :: 3.10
Classifier: Programming Language :: Python :: 3.11
Classifier: Programming Language :: Python :: 3.12
Classifier: License :: OSI Approved :: Apache Software License
Requires-Python: >=3.10
License-File: LICENSE
Requires-Dist: pyyaml>=6.0
Requires-Dist: fastcore>=1.5.0
Requires-Dist: python-fasthtml>=0.1.0
Requires-Dist: nbformat>=5.7.0
Requires-Dist: nbconvert>=7.2.0
Requires-Dist: beautifulsoup4>=4.12.0
Requires-Dist: MonsterUI>=0.1.0
Provides-Extra: dev
Dynamic: author
Dynamic: author-email
Dynamic: classifier
Dynamic: description
Dynamic: description-content-type
Dynamic: home-page
Dynamic: keywords
Dynamic: license
Dynamic: provides-extra
Dynamic: requires-dist
Dynamic: requires-python
Dynamic: summary
